apiconnectors/__init__.py
apiconnectors/jira/__init__.py
apiconnectors/jira/jira_admin.py
apiconnectors/jira/jira_cloud.py
apiconnectors/mattermost/__init__.py
apiconnectors/mattermost/client.py
apiconnectors/vault/__init__.py
apiconnectors/vault/client.py
connectors_test-1.0.11.dist-info/LICENSE
connectors_test-1.0.11.dist-info/METADATA
connectors_test-1.0.11.dist-info/WHEEL
connectors_test-1.0.11.dist-info/RECORD
