Metadata-Version: 2.1
Name: connectors-test
Version: 1.0.11
Summary: A set of API utility connectors
License: LGPL-3.0
Author: ali-kelkawi
Requires-Python: >=3.8,<4.0
Classifier: License :: OSI Approved :: GNU Lesser General Public License v3 (LGPLv3)
Classifier: Programming Language :: Python :: 3
Classifier: Programming Language :: Python :: 3.8
Classifier: Programming Language :: Python :: 3.9
Classifier: Programming Language :: Python :: 3.10
Classifier: Programming Language :: Python :: 3.11
Classifier: Programming Language :: Python :: 3.12
Provides-Extra: jira
Provides-Extra: mattermost
Provides-Extra: vault
Requires-Dist: hvac (==2.1.0) ; extra == "vault"
Requires-Dist: jira (==3.6.0) ; extra == "jira"
Requires-Dist: mattermostdriver (==7.3.2) ; extra == "mattermost"
Requires-Dist: python-dateutil (==2.8.2) ; extra == "vault"
